Workbook

Sheet Sommaire
B3: Fonctionnalités | C3: Validation Logicielle | D3: Assurance Qualité | E3: Total | F3: Heures de retard (-10%)/heure | G3: Poids | H3: Note pondérée
A4: Sprint 1 | B4: =(Fonctionnalités!D14) -> 0.96 | C4: =Fonctionnalités!D18 -> 0.69 | D4: ='Assurance Qualité'!C59 -> 0.7515 | E4: =B4*0.5+C4*0.1+D4*0.4 - 0.1*F4 -> 0.8496 | G4: 20 | H4: =E4*G4 -> 16.992
A5: Sprint 2 | B5: =(Fonctionnalités!D28) -> 0.945 | C5: =Fonctionnalités!D33 -> 0.71 | D5: ='Assurance Qualité'!F59 -> 0.7305 | E5: =B5*0.5+C5*0.1+D5*0.4 - 0.1*F5 -> 0.8357 | G5: 25 | H5: =E5*G5 -> 20.8925
A6: Sprint 3 | B6: =(Fonctionnalités!D43) -> 0.965 | C6: =Fonctionnalités!D48 -> 0.92 | D6: ='Assurance Qualité'!I59 -> 0.65 | E6: =B6*0.5+C6*0.1+D6*0.4 - 0.1*F6 -> 0.8345 | G6: 25 | H6: =E6*G6 -> 20.8625
A7: UX | E7: =MIN(1,1+SUM(A12:A56)) -> 0.86 | G7: 5 | H7: =E7*G7 -> 4.3
A9: Commentaire UX | C9: Alice
B10: Commentaires
B11: Vue Admin&Édition
A12: -0.01 | B12: scroll vertical
A13: 0.02 | B13: indicateur de champ non rempli cool
A14: -0.01 | B14: il y avait pas vraiment besoin de séparer tuiles et objets en deux tabs, on a la place et c'est juste un clic supplémetaire
A15: 0.05 | B15: prévisualisation de placement
A16: -0.01 | B16: erreur de validation case accessible/porte pas très visible. Idéalement, il y aura et le contour rouge et un texte
A17: -0.01 | B17: Visible rouge et visible vert perso jsp ce que ça veut dire (utiliser une icone plutôt)
A18: -0.04 | B18: aucun warning avant de supprimer une carte, reset, quitter, expluser etc
B19: Vue Création de Match, Personnage, Join et Page d'attente
A20: -0.01 | B20: explique pas les erreurs qui fait qu'on peut pas confirmer le form de création
A21: -0.01 | B21: fonctionnement de dés+modifiers pas clair
A22: -0.02 | B22: scrollbar dans les box dans la salle d'attente
A23: -0.01 | B23: cliquer sur envoyer avec la souris perd le focus de textbox clavardage
A24: -0.01 | B24: commencer la partie pourrait être grisé si impair
B25: Vue de jeu
A26: -0.01 | B26: bouton action cliquable même si pas d'action autour
A27: -0.01 | B27: timer peu visible
A28: -0.02 | B28: scroll à l'intérieur de la carte pour combat
A29: 0.01 | B29: combat clair
A30: -0.01 | B30: équipe bleu bleu sur fond bleu pas lisible
A31: -0.01 | B31: messages de fin de partie pas personnalisé
A32: -0.01 | B32: Nom de la team gagnante en anglais
B33: Stats
A34: -0.02 | B34: n'affiche pas les équipes
A35: -0.01 | B35: tri sur nom du joueur impossible
A36: -0.01 | B36: gagants pas affichés
B37: Global
A38: 0.03 | B38: UI, thème, cohérence, layout

Sheet Assurance Qualité
A2: Grille de correction LOG2990
A4: Assurance Qualité
A6: Critère | B6: Description | C6: Sprint 1 | F6: Sprint 2 | I6: Sprint 3
C7: Note | D7: Poids | E7: Commentaires | F7: Note | G7: Poids | H7: Commentaires | I7: Note | J7: Poids | K7: Commentaires
A8: 1. Projet | C8: Correcteur | E8: Zachary | F8: Correcteur | H8: Zachary | I8: Correcteur
A9: 1.1 Utilisation des Cadriciels | B9: Le projet respecte les meilleures pratiques des cadriciels utilisés. (Exemple: séparation des responsabilités dans les Components et Services d'Angular, syntaxe moderne d’Angular, respect de la sémantique HTTP avec Express, etc.) | C9: 0.25 | D9: 6 | E9: -0,25 possibilité de fuite de mémoire dans edition-page.component.ts (le subscription reste après suppression) -0.25 Les composants et les services ne doivent pas exporter d'interfaces, de types, d'enums... Utilisez des fichiers dédiés (edition.service.ts) -0, 25 les services doivent être privés et readonly dans les components et accédés par des méthodes par le HTML ou au moins être protected au lieu de public | F9: 0.75 | G9: 6 | H9: -0.25 definition des enums et d'interfaces dans les components | I9: 0 | J9: 6 | K9: -0,25 game-combat-popup.component.ts ne devrait pas contenir le style pour le template html. Il devrait y avoir un fichier de css ou scss dans le même dossier -0,25 plusieurs de vos services exportent des types -0,25 Vos services injectés devraient être private/protected et readonly (action-service.ts, combat-service.ts,...) -0,25 définition d'enum, d'interface et de type dans des services (items-validator.service.ts, iactive-game.service.ts, gameplay-flag-decision.service.ts, virtual-player-sactuary.service.ts)
A10: 1.2 Arborescence | B10: Le projet respecte une arborescence de fichiers claire, uniforme et structurée. Les noms de fichiers et dossiers respectent le format kebab-case. | C10: 0.75 | D10: 2 | E10: -0,25 AvatarI.ts n'est pas en kebab-case | F10: 1 | G10: 2 | I10: 1 | J10: 2
A11: Sous-total | C11: =SUMPRODUCT(C6:C10,D6:D10) -> 3 | D11: =SUM(D6:D10) -> 8 | F11: =SUMPRODUCT(F6:F10,G6:G10) -> 6.5 | G11: =SUM(G6:G10) -> 8 | I11: =SUMPRODUCT(I6:I10,J6:J10) -> 2 | J11: =SUM(J6:J10) -> 8
A12: 2. Classe | C12: Correcteur | E12: Alice | F12: Correcteur | H12: Alice | I12: Correcteur | K12: Alice
A13: 2.1 Responsabilité | B13: La classe n'a qu'une responsabilité claire. | C13: 1 | D13: 3 | E13: votre form-component contient trop de logique qui pourrait être dans un service à la place | F13: 0.5 | G13: =D13 -> 3 | H13: -0.5 server/game-sockets.service.ts a trop de responsabilités. Vous essayez d'utiliser un seul et unique service de socket ce qui fait que ce fichier a beaucoup de reponsabilités (connexion et rooms, gestion de lobby, déroulement d'une partie, abandon/déconnexion, etc.). Vous avez d'ailleurs bien réussi à séparer les responsabilités correctemebt avec debugSocketService. C'est dommage de ne pas avoir séparer à minima ce qui concerne les lobbys (connexion, expulsion etc.) du déroulement d'une partie (dépalcement etc.) | I13: 0.6 | J13: =G13 -> 3 | K13: -0.2 active-game.service.ts a trop de responsabilités. Il gère l'entièreté des actions de jeu, socket mais aussi state du ui, calcul de reachability/movement etc. -0.2 gameplay combat.service.ts gère un peu trop d'aspects. Aurait pu diviser la gestion d'attaque (position, dégats) et celle globale du combat (tours, hp etc.)
A14: 2.2 Attributs | B14: La classe comporte uniquement des attributs utilisés. La classe comporte uniquement des attributs qui sont des états de la classe. La classe ne comporte pas d'attribut utilisé seulement dans les tests. | C14: 0.6 | D14: 2 | E14: -0.2 game-table.component.ts timeout n'est pas un état de classe, et devrait juste être une constante. Même chose pour wait-page.component.ts timeout -0.2 edition.service.ts spawnpointMaxAmount, flagMaxAmount, sanctuaryMaxAmount ne sont pas des états de classe | F14: 0.8 | G14: =D14 -> 2 | H14: -0.2 game.component.ts totalRows est assigné mais jamais lu | I14: 1 | J14: =G14 -> 2
A15: 2.3 Accessibilité | B15: La classe minimise l'accessibilité des membres. (Bonne utilisation de public/private/protected pour les attributs et les fonctions) Les méthodes get/set font une validation quelconque sur les attributs privés. | C15: 0 | D15: 2 | E15: pénalité pour chaque fichier contenant des erreurs d'accessibilité (attribut ou fonction utilisé uniquement dans leur propre class ou leur classe de test, qui pourrait donc être privé) -0.2 edition-cell.component.ts getSanctuaryBgPosition -0.2 game-edition.component.ts previousVersion, isRightClick, currentCell, lastIndexes, isShiftPressed... -0.2 game-creation-dialog.component.ts size -0.2 game-table.component.ts fetchCorrectGames, timeout, adminSocketService etc. -0.2 administration.service.ts gameService -0.2 edition.service.ts blockingCells, sanctuaryMaxAmount, cellBelongsToObjectupdateMaxAmount etc. -0.2 game-edit-form.service.ts gameService, getPreviewImage | F15: 0 | G15: =D15 -> 2 | H15: -0.2 game.component.ts tileInfoPlayerAvatarUrl, tileInfoPlayerName, tileInfoItemDescription, tileInfoItemTitle, tileInfoMovementCost etc. -0.2 game-attack.component.ts localPlayerService est protected mais devrait être privé -0.2 player-info.component.ts localPlayerService, activeGameService - player-list.component.ts, wait-chat-sidebar.component.ts, wait-player-list.component.ts activeGameService -0.2 form-page.component.ts gameId, navigator, router, localPlayerService, toastService, characterFormService -0.2 wait-page.comnponent.ts waitGridService -0.2 edition.service objectSizesMap, boardSharedService | I15: 0 | J15: =G15 -> 2 | K15: -0.2 editor-tool.component.ts gameEditFormService -0.2 game-combat-outcome.component localPlayerName, combatTimeLeftSeconds -0.2 game-ended.component.ts cancellationReason -0.2 game-player-card.component.ts fightSanctuaryBonus -0.2 editor-page.component.ts -0.2 game-popup-state.service.ts sanctuaryPopupDescription, sanctuaryPopupEffectLabel, sanctuaryPopupTitle -0.2 wait-grid.service gameCells
A16: 2.4 Couplage | B16: La classe minimise le couplage aux autres classes. La classe minimise les longues chaînes d'appels (ex : foo.bar.baz.foo) | C16: 1 | D16: 4 | F16: 0.5 | G16: =D16 -> 4 | H16: -0.25 Vous avez plusieurs composants avec des couplages relativement élevés (join-form-page, game-page, administration-page, wait-page). Normalement je pénalise de -0.25 pour chacun des fichiers, mais puisqu'ils sont tous à peine au dessus du seuil de couplage je ne vous enlève des points qu'une fois. -0.25 game-sockets.service.ts a 5 services + 5 autres services dans GameplayServices injectés. Voir commentaire dans 2.1 | I16: 0.75 | J16: =G16 -> 4 | K16: -0.25 game-page.facade injectent 7 services. Je comprends que c'est sa responsabilité de façade mais le couplage reste élevé avec game-page component (qui lui-même injecte des services) ce qui réduit l'isolation
A17: 2.5 Valeur par défaut | B17: La classe initialise tous ses attributs de la même façon. Soit à la définition, soit dans le constructeur. | C17: 1 | D17: 4 | F17: 0.9 | G17: =D17 -> 4 | H17: -0.1 la plupart de votre client injectent ses dépendances à la définition, mais game-turn.service le fait dans le constructeur | I17: 1 | J17: =G17 -> 4
A18: Sous-total | C18: =SUMPRODUCT(C13:C17,D13:D17) -> 12.2 | D18: =SUM(D13:D17) -> 15 | F18: =SUMPRODUCT(F13:F17,G13:G17) -> 8.7 | G18: =SUM(G13:G17) -> 15 | I18: =SUMPRODUCT(I13:I17,J13:J17) -> 10.8 | J18: =SUM(J13:J17) -> 15
A19: 3. Fonctions et méthodes | C19: Correcteur | E19: Zachary | F19: Correcteur | H19: Zachary | I19: Correcteur | K19: Zachary
A20: 3.1 Utilité | B20: La fonction est utilie et non-triviale. La fonction a une responsabilité claire. La fonction n'a pas une longueur trop grande. | C20: 1 | D20: 3 | F20: 0.5 | G20: 3 | H20: -0,25 client/src/app/services/gameplay/active-game.service.ts:55 le constructeur est trop long. Il faut le réduire en appelant des méthodes au lieu d'avoir de la logique dans les fonction .on() de SocketIO -0,25 même chose dans server/app/services/realtime/game-sockets.service.ts:32 et server/app/services/realtime/debug-socket.service.ts:17 | I20: 0 | J20: 3 | K20: -0,25 Fonction applyCombatTurn() dans combat-service.ts:45 : Fonction trop longue (80 lignes) et aurait pu être découpée -0,25 Fonction handleActiveGameDisconnect() dans game-session.service.ts:80 : Fonction trop longue (51 lignes) et aurait pu être découpée. -0,25 Fonction moveToIndex() dans virtual-player.utilities.ts:173 : Fonction trop longue (58 lignes) et aurait pu être découpée. -0,25 Fonction handleError() dans game.service.ts:60 : Paramètre non utilisé 'request'.
A21: 3.2 Paramètres | B21: La fonction possède le moins de paramètres possibles en entrée. La fonction possède uniquement des paramètres d'entrée qui sont utilisés. | C21: 1 | D21: 3 | F21: 1 | G21: 3 | I21: 0.5 | J21: 3 | K21: -0,5 beaucoup de fonctions prennent en parametre une paire de rowIndex et colIndex en plus de d'autres paramètres. Les simplifier en une structure de donnée de 2 numbers aurait été mieux
A22: Sous-total | C22: =SUMPRODUCT(C20:C21,D20:D21) -> 6 | D22: =SUM(D20:D21) -> 6 | F22: =SUMPRODUCT(F20:F21,G20:G21) -> 4.5 | G22: =SUM(G20:G21) -> 6 | I22: =SUMPRODUCT(I20:I21,J20:J21) -> 1.5 | J22: =SUM(J20:J21) -> 6
A23: 4. Gestion des ressources et erreurs | C23: Correcteur | E23: Alice | F23: Correcteur | H23: Alice | I23: Correcteur | K23: Alice
A24: 4.1 Console | B24: La console ne génère pas de message d'avertissement (warning) ou d'erreur (error) qui aurait pu être gérés par le programme. | C24: 1 | D24: 1 | F24: 1 | G24: 1 | I24: 1 | J24: 1
A25: 4.2 Code asynchrone | B25: Le code asynchrone (Promise, Observable, Event) est géré adéquatement. | C25: 1 | D25: 2 | F25: 1 | G25: 2 | I25: 1 | J25: 2
A26: 4.3 Messages d'erreur | B26: Les messages d'erreur sont précis et compréhensibles par l'utilisateur moyen. | C26: 1 | D26: 1 | F26: 1 | G26: 1 | I26: 1 | J26: 1
A27: Sous-total | C27: =SUMPRODUCT(C24:C26,D24:D26) -> 4 | D27: =SUM(D24:D26) -> 4 | F27: =SUMPRODUCT(F24:F26,G24:G26) -> 4 | G27: =SUM(G24:G26) -> 4 | I27: =SUMPRODUCT(I24:I26,J24:J26) -> 4 | J27: =SUM(J24:J26) -> 4
A28: 5. Variables et constantes | C28: Correcteur | E28: Zachary | F28: Correcteur | H28: Zachary | I28: Correcteur | K28: Zachary
A29: 5.1 Groupement | B29: Les constantes sont regroupées ensemble en groupes logiques. | C29: 0 | D29: 2 | E29: -1 vous ne mettez pas vos constantes dans un fichier séparé (edition.service.ts, form-page.component.ts, terrain-validator.service.ts, ...) | F29: 0.5 | G29: =D29 -> 2 | H29: -0,5 character-form.service.ts (2), terrain-validator.service.ts, player-info.component.ts | I29: 1 | J29: =D29 -> 2
A30: 5.2 Environnement | B30: Des variables d'environnements sont utilisées lorsque possible. | C30: 1 | D30: 2 | F30: 1 | G30: =D30 -> 2 | I30: 1 | J30: =D30 -> 2
A31: 5.3 Contexte d'utilisation | B31: La constante est utilisé dans un contexte lié à la logique d'affaire. (Exemple d'erreur: const DEUX = 2, bonne utilisation: WAIT_TIME = 5000 ) | C31: 1 | D31: 2 | F31: 0.9 | G31: =D31 -> 2 | H31: -0,1 ALL_EXCEPT_ONE_PLAYER_ABANDONED = 1 pourrait être quelque chose du genre MIN_PLAYER_COUNT | I31: 1 | J31: =D31 -> 2
A32: Sous-total | C32: =SUMPRODUCT(C29:C31,D29:D31) -> 4 | D32: =SUM(D29:D31) -> 6 | F32: =SUMPRODUCT(F29:F31,G29:G31) -> 4.8 | G32: =SUM(G29:G31) -> 6 | I32: =SUMPRODUCT(I29:I31,J29:J31) -> 6 | J32: =SUM(J29:J31) -> 6
A33: 6. Expressions booléennes | C33: Correcteur | E33: Alice | F33: Correcteur | H33: Alice | I33: Correcteur | K33: Alice
A34: 6.1 Expression | B34: Pas de comparaisons inutiles dans une expression booléenne. (Exemple d'erreur: x === true) | C34: 0.75 | D34: 2 | E34: -0.25 form-page.component.ts "if (next === null)" plutôt que juste "if (next)" | F34: 0.75 | G34: 2 | H34: -0.25 "if (this.selectedObject === null) return;" Aussi "!activeGame || !activeGame.game || !activeGame.game.board" pourrait juste être "!activeGame?.game?.board" | I34: 0 | J34: 2 | K34: -0.25 "if (!isSanctuaryItem(item) || item.active === false)" et "return item.active === true || …" -0.25 "if (type !== undefined && this.hasManda" -0.25 " if (cellType === undefined) {" -0.25 "if (doorCell === undefined)" -0.25 "if (this.hoveredObject === null) {"
A35: 6.2 Logique négative | B35: L'expression booléenne évite la logique négative. (Exemple d'erreur: if( !notFound(…) ) | C35: 1 | D35: 2 | F35: 0.5 | G35: 2 | H35: -0.25 Condition négative "if (!gameHasStarted) { await this.handleWaitingRoomDisconnect(gameId, playerId); } else { await this.handleActiveGameDisconnect(gameId, playerId); }" -0.25 Condition négative "this.activeGame.currentPlayerIndex = nextIndex !== -1 ? nextIndex : Math.min(this.activeGame.currentPlayerIndex, this.activeGame.turnOrder.length - 1);" condition négative (if (!x) b.. else a..) et donc inversée pour aucune raison (if (x) a... else b...) | I35: 0.75 | J35: 2 | K35: -0.25 "if (!activeGame.isDebugMode) { attackDiceBonus = this.rollDice(character.attackBonusDiceType); } else { attackDiceBonus = this.getMaxDice(character.attackBonusDiceType, character.name, activeGame); }" et "if (!activeGame.isDebugMode) { defenseDiceBonus = this.rollDice(character.defenseBonusDiceType); } else { defenseDiceBonus = this.getMaxDice(character.defenseBonusDiceType, character.name, activeGame); }"
A36: 6.3 Ternaire | B36: Bonne utilisation des expressions ternaires. Pas d'imbrications de ternaires qui nuisent à la compréhension de l'expression booléenne | C36: 0.8 | D36: 3 | E36: -0.2 game-edit-form.component.ts "if (id) { observable = this.gameService.saveGame(id, gameData); } else { observable = this.gameService.createGame(gameData); }" plutôt que: "observable = id ? this.gameService.saveGame(id, gameData) : this.gameService.createGame(gameData)" | F36: 0.6 | G36: 3 | H36: -0.2 "if (this.boardEditorService.gameMode === GameType.Ctf) { return baseAvailableItemTypes.concat([ItemType.Flag]); } return baseAvailableItemTypes;" plutôt que "return this.boardEditorService.gameMode === GameType.Ctf ? baseAvailableItemTypes.concat([ItemType.Flag]) : baseAvailableItemTypes;" -0.2 "if (diceType === DiceSelectionType.D4AttackAndD6Defense) { return DiceType.SixSided; } else { return DiceType.FourSided; }" x2 en plus | I36: 0 | J36: 3 | K36: -0.2 final-player-list.component.ts "if (this.statOrderService.direction === OrderDirection.Ascending) { return 'assets/end/arrow-up.svg'; } else { return 'assets/end/arrow-down.svg'; }" -0.2 stat-order.service.ts "if (this.direction === OrderDirection.Ascending) { this.direction = OrderDirection.Descending; } else { this.direction = OrderDirection.Ascending; }" -0.2 "if (!item) { return null; } return ITEM_INFO_BY_TYPE[item.itemType] ?? null;" -0.2 "if (!(target instanceof HTMLElement)) return false; return target.matches('[data-chat-message-input]');" -0.2 ""if (!activeGame.isDebugMode) { attackDiceBonus = this.rollDice(character.attackBonusDiceType); } else { attackDiceBonus = this.getMaxDice(character.attackBonusDiceType, character.name, activeGame); }" et "if (!activeGame.isDebugMode) { defenseDiceBonus = this.rollDice(character.defenseBonusDiceType); } else { defenseDiceBonus = this.getMaxDice(character.defenseBonusDiceType, character.name, activeGame); }""
A37: 6.4 Prédicats | B37: L'expression booléenne est simple. (Exemple d'erreur : if(a && b && !c || d) L'expression booléenne utilise un ou des prédicats pour simplifier une condition complexe. | C37: 0.75 | D37: 3 | E37: -0.25 reachability-validator.service.ts "if ( newRow >= 0 && newRow < rows && newCol >= 0 && newCol < cols && !visited[newRow][newCol] && board.cells[newRow][newCol] !== CellType.Wall )" | F37: 0.75 | G37: 3 | H37: -0.25 "return row >= 0 && row < rows && col >= 0 && col < cols && !visited[row][col] && board.cells[row][col] !== CellType.Wall;" | I37: 0 | J37: 3 | K37: -0.25 "if ( !playerAtPosition && currentPlayer && boardItem && isSanctuaryItem(boardItem) && isSanctuaryActive(boardItem) && isPositionAdjacentToSanctuary(currentPlayer.currentPosition, boardItem) )" -0.25 "return ( (position.x === sanctuary.x - 1 && isWithinSanctuaryRows) || (position.x === sanctuary.x + 2 && isWithinSanctuaryRows) || (position.y === sanctuary.y - 1 && isWithinSanctuaryColumns) || (position.y === sanctuary.y + 2 && isWithinSanctuaryColumns) );" ,-0.25 "return ( (position.x === sanctuary.x - 1 && isWithinSanctuaryRows) || (position.x === sanctuary.x + 2 && isWithinSanctuaryRows) || (position.y === sanctuary.y - 1 && isWithinSanctuaryColumns) || (position.y === sanctuary.y + 2 && isWithinSanctuaryColumns) );" ,-0.25 "if (rows === 0 || cols === 0 || rowIndex < 0 || colIndex < 0 || rowIndex + 1 >= rows || colIndex + 1 >= cols)" -0.25 "return rowIndex >= 0 && rowIndex < this.gameCells.length && colIndex >= 0 && colIndex < (this.gameCells[0]?.length ?? 0);" -0.25 "return ( row >= 0 && row < cells.length && col >= 0 && col < cells[0].length && !visited[row][col] && cells[row][col] !== CellType.Wall && !blockedCells.has(getCellKey(row, col)) );" ,-0.25 "return ( row >= 0 && row < rows && col >= 0 && col < cols && !visited[row][col] && board.cells[row][col] !== CellType.Wall && !blockedCells.has(`${row},${col}`) );" -0.25 "return (player.fightSanctuaryUsed ?? false) || (player.fightSanctuaryTurnsRemaining ?? 0) > 0 || (player.fightSanctuaryBonus ?? 0) > 0; }"
A38: Sous-total | C38: =SUMPRODUCT(C34:C37,D34:D37) -> 8.15 | D38: =SUM(D34:D37) -> 10 | F38: =SUMPRODUCT(F34:F37,G34:G37) -> 6.55 | G38: =SUM(G34:G37) -> 10 | I38: =SUMPRODUCT(I34:I37,J34:J37) -> 1.5 | J38: =SUM(J34:J37) -> 10
A39: 7. Qualité générale | C39: Correcteur | E39: Beaurel | F39: Correcteur | H39: Beaurel | I39: Correcteur | K39: Beaurel
A40: 7.1 Langue | B40: La langue utilisée pour le code source est uniforme pour tout le code source. La langue utilisée pour les commentaires doit être uniforme, mais peut être différente que la langue du code source. | C40: 1 | D40: 2 | E40: OK | F40: 0.2 | G40: =D40 -> 2 | H40: 1 -0,2 TEMPS_PREPA_TOUR, TEMPS_TOUR, PRIX_PORTE_GAZON, PRIX_GLACE, PRIX_EAU, TEMPS_ECRAN_FIN_PARTIE vs DEFAULT_PLAYER_LIFE_POINTS, COUNTDOWN_TICK_INTERVAL_MS constants.ts:22-37 2 -0,2 positionDepart, positionGrille vs currentHealth, attackPoints character.ts:19-22 3 -0,2 // match "PlayerName - 1234" et capture "PlayerName" et "1234" — commentaire FR dans code EN active-game.service.ts:118 4 -0,2 baseDix — identifiant FR dans code EN server.ts:14 | I40: 0.6 | J40: =D40 -> 2 | K40: 1) -0,20 TEMPS_PREPA_TOUR, TEMPS_TOUR, PRIX_PORTE_GAZON, PRIX_GLACE, PRIX_EAU, TEMPS_ECRAN_FIN_PARTIE vs DEFAULT_PLAYER_LIFE_POINTS, COUNTDOWN_TICK_INTERVAL_MS — constants.ts:22-37 ; 2) -0,20 positionDepart, positionGrille vs currentHealth, attackPoints — character.ts:19-22 ; 3) -0,20 commentaire FR dans code EN — active-game.service.ts:118 ; 4) -0,20 baseDix — identifiant FR dans code EN — server.ts:14.
A41: 7.2 Commentaire | B41: Le commentaire est pertinent. (Pas de code mort commenté) | C41: 1 | D41: 2 | E41: Ok | F41: 0.6 | G41: =D41 -> 2 | H41: -0,2 //unique: true, — ligne de code commentée game.ts:12 -0,2 commentaire inutile dans initialize game-sockets.service.ts:37 | I41: 0.8 | J41: =D41 -> 2 | K41: -0,20 //unique: true, ligne de code commentée — game.ts:12 ; -0,20 commentaire inutile dans initialize — game-sockets.service.ts:37.
A42: 7.3 Enum | B42: Le code utilise des enum lorsque c'est pertinent. | C42: 0 | D42: 2 | E42: -0.2 type Tool = 'placement' | 'objects' | 'erase' un enum devrait être utilisé ici à la place d'un type edition.service.ts -0,2 type BonusType = 'life' | 'speed' un enum devrait être utilisé ici à la place d'un type character.model.ts -0,2 type DiceSelectionType = 'attack' | 'defense' un enum devrait être utilisé ici à la place d'un type character.model.ts -0,2 type DimensionSize = 'small' | 'medium' | 'large' un enum devrait être utilisé ici à la place d'un type game-creation-dialog.component.ts -0,2 responseType?: 'json' | 'text' | 'blob' | 'arraybuffer' un enum devrait être utilisé ici à la place d'un type union | F42: 0.8 | G42: =D42 -> 2 | H42: -0,20 item.itemType !== 'startingPosition' — un enum devrait être utilisé ici (ItemType.StartingPosition existe déjà) active-game.service.ts:410 | I42: 0.8 | J42: =D42 -> 2 | K42: -0,20 item.itemType !== 'startingPosition' — un enum devrait être utilisé (ItemType.StartingPosition existe) — active-game.service.ts:410.
A43: 7.4 Classe et interface | B43: Le code n'utilise pas d'objets anonymes JS et priorise les classes et les interfaces. | C43: 0.4 | D43: 4 | E43: -0,2 getExpectedCounts(): { expectedStartingPoints: number; expectedLifeSanctuaries: number; expectedFightSanctuaries: number } | null une interface devrait être utilisée ici items-validator.service.ts -0,2 mapOptions(): { headers?: Record<string, string>; params?: HttpParams; responseType?: 'json'; withCredentials?: boolean; } une interface devrait être utilisée ici angular-http-client-adapter.ts -0,2 dimensionOptions: { value: DimensionSize; label: string; displaySize: string }[] une interface devrait être utilisée ici game-creation-dialog.component.ts | F43: 0 | G43: =D43 -> 4 | H43: 1 -0,20 defenderNewPosition: { x: number; y: number } — l'interface Position existe et devrait être utilisée attackResult.ts:6 2 -0,20 Promise<{ newPosition: Position; movementLeft: number }> — une interface devrait être utilisée movement-service.ts:18 3 -0,20 const queue: { pos: Position; costSoFar: number }[] — une interface devrait être utilisée movement-service.ts:53 4 -0,20 getCurrentPlayer(activeGame: { players: ICharacter[]; currentPlayerIndex: number; turnOrder: string[] }) — une interface devrait être utilisée turn-service.ts:103 5 -0,20 { gameId: this.activeGame._id, playerId: playerName } — objet anonyme passé à socket.emit() dans 3 méthodes active-game.service.ts:262 | I43: 0 | J43: =D43 -> 4 | K43: 14 × -0,20 (cap -4) — types objets anonymes : attackResult.ts:6 (defenderNewPosition: { x; y }), movement-service.ts:18 et :53 (Promise<{ newPosition: Position; movementLeft: number }> et const queue: { pos: Position; costSoFar: number }[]), turn-service.ts:103 (activeGame: { players: ICharacter[]; currentPlayerIndex: number; turnOrder: string[] }), sanctuary-service.ts:116/139/154/187 (player: { actionsLeft: number } / { currentPosition: Position } / { currentHealth: number; initialHealth: number }), socket-error.ts:4 (return { errorCodes: ErrorCode[] }), debug-socket.service.ts:96 (players: { name: string; hasAbandoned: boolean; currentPosition: Position }[]), socket.service.ts:17 (cors), virtual-player-sanctuary.service.ts:75 + autres signatures. L'interface Position et autres existent.
A44: 7.5 Duplication | B44: Il n'y a pas de duplication de code. | C44: 0.4 | D44: 6 | E44: -0,2 Duplication de fetchGames() / fetchVisibleGames() (quasi identiques) dans game-table.service.ts passez un parametre -0,2 Duplication de type DiceSelectionType = 'attack' | 'defense' dans character.model.ts, dice-selector.component.ts, character-modifier-panel.component.ts, et form-page.component.ts (4 fois) -0,2 Duplication de la vérification de bornes row < 0 || row >= board.cells.length || col < 0 || col >= board.cells[0].length dans isWall() et isTerrain() de door-validator.service.ts | F44: 0.8 | G44: =D44 -> 6 | H44: -0,20 getImageForAvatar() identique dans 2 composants avatar-preview.component.ts + avatar-grid.component.ts | I44: 0.8 | J44: =D44 -> 6 | K44: -0,20 getImageForAvatar() identique dans avatar-preview.component.ts et avatar-grid.component.ts.
A45: 7.6 ESLint | B45: Il n'y a pas de "eslint:disable" non justifiés dans le code. L'utilisation limitée de eslint:disable est tolérée dans les fichiers de test (.spec.ts). (Exemple : nombres magiques) | C45: 1 | D45: 8 | E45: Ok | F45: 1 | G45: =D45 -> 8 | I45: 1 | J45: =D45 -> 8
A46: 7.7 Complexité | B46: Le code minimise la complexité cyclomatique. (Exemple : plusieurs if/else ou boucles for imbriqués, opérations complexes, etc.) | C46: 1 | D46: 6 | E46: validateGameData() — complexité cyclomatique élevée (~9, avec 8 branches if enchaînées) Attention | F46: 0.8 | G46: =D46 -> 6 | H46: -0,2 la fonction intialize dans game-sockets.service,ts très longue vous pouvez decouper en plusieurs fonctions | I46: 0.8 | J46: =D46 -> 6 | K46: -0,2 — fonctions à complexité cyclomatique élevée (≥12) : agressive-player.service.ts:21 play (22), active-game.controller.ts:22 configureRouter (17), game.controller.ts:27 configureRouter (17), game-interaction.service.ts:49 handleGridCellClick (15), end-game.service.ts:30 checkEndGame (14), door-service.ts toggleDoor (13), debug-socket.service.ts register (13), virtual-player.utilities.ts findClosestReachablePlayer (13), turn-service.ts beginTurn (12), ctf-objective.service.ts handleTurnObjective (12), game-sockets.service.ts initialize (très longue).
A47: 7.7 Nomenclature des variables, classes et méthodes | B47: Les noms des variables, classes et méthodes sont précis et clairs. Les noms respectent un format unique: camelCase pour les variables et méthodes, SCREAMING_SNAKE_CASE pour les constantes, etc . Les noms ne sont pas troncés excessivement. (Exemple: utiliser background au lieu de seulement bg). | C47: 0.8 | D47: 6 | E47: -0,2 timeout = 4000 (constante utilisée comme valeur fixe) game-table.component.ts | F47: 0.7 | G47: =D47 -> 6 | H47: -0,30 V, pq, d, u, v, w — variables tronquées excessivement dijkstra.ts:6-27 | I47: 0.6 | J47: =D47 -> 6 | K47: -0,40 V, pq, d, u, v, w — variables tronquées excessivement — dijkstra.ts:6-27.
A48: 7.8 Performance | B48: Le logiciel a une performance acceptable. | C48: 1 | D48: 4 | E48: Ok | F48: 0.7 | G48: =D48 -> 4 | H48: -0.3 Mauvaise performance lors de la correction. Des temps d'attente de plus de 5secondes parfois entre les pages | I48: 1 | J48: =D48 -> 4
A49: Sous-total | C49: =SUMPRODUCT(C40:C48,D40:D48) -> 30.8 | D49: =SUM(D40:D48) -> 40 | F49: =SUMPRODUCT(F40:F48,G40:G48) -> 27.8 | G49: =SUM(G40:G48) -> 40 | I49: =SUMPRODUCT(I40:I48,J40:J48) -> 29.6 | J49: =SUM(J40:J48) -> 40
A50: 8. Gestion de versions | C50: Correcteur | E50: Zachary | F50: Correcteur | H50: Zachary | I50: Correcteur | K50: Zachary
A51: 8.1 Tag et remise | B51: Le commit de remise possède le bon tag. (sprint1, sprint2, sprint3) | C51: 1 | D51: 2 | F51: 1 | G51: 2 | I51: 1 | J51: 2
A52: 8.2 Commits | B52: Les commits ont un message pertinent, descriptif et structuré selon une convention quelconque. | C52: 0 | D52: 2 | E52: -0,5 beaucoup de mélange de français et d'anglais dans les commits -0,5 beaucoup de commit manquent de clarté (efcb0cad, dba0f1fc, 24b7eaa, fd098155, 57fde642, 4e727ac1, ...) | F52: 0.6 | G52: 2 | H52: -0,4 messages de commit qui ne sont pas clairs: 0b2f933 Dev ec48d59 Hotfix/gitlab 79287fa Hotfix/gitlab 430a3f2 Hotfix/url Attention à votre formatage, plusieurs formats de messages de commits | I52: 1 | J52: 2
A53: 8.3 Branches mortes | B53: Le projet ne contient pas de branches mortes (stale branch). Une branche est considérée comme morte si elle n'a pas de commit pendant plus de 3 semaines. | C53: 1 | D53: 1 | F53: 1 | G53: 1 | I53: 1 | J53: 1
A54: 8.4 Gitlab | B54: Des Merge Requests sont utilisées pour fusionner vers la branche de production. Une Merge Request est revue par au moins un membre de l'équipe avant la fusion. Les Issues sont mis à jour tout au long du projet. | C54: 0.5 | D54: 4 | E54: -0.25 des MR sont fussionnées mais pas approuvées : !13, !16, !17 et d'autres ont des pipeline qui échouent: !18 -0,25 Des MR sont entre des branches secondaires : !16,!17,!13,!18 | F54: 1 | G54: 4 | I54: 0.65 | J54: 4 | K54: -0,25 !201 est une MR entre branches secondaires -0,1 issue #26 et #27 non assignées et non complétées
A55: 8.5 Fichiers | B55: Le projet contient uniquement les fichiers nécessaires. (Exemple: pas de dossier node_modules ou coverage, pas de fichiers package.json à la racine, etc.). | C55: 1 | D55: 2 | F55: 1 | G55: 2 | I55: 1 | J55: 2
A56: Sous-total | C56: =SUMPRODUCT(C51:C55,D51:D55) -> 7 | D56: =SUM(D51:D55) -> 11 | F56: =SUMPRODUCT(F51:F55,G51:G55) -> 10.2 | G56: =SUM(G51:G55) -> 11 | I56: =SUMPRODUCT(I51:I55,J51:J55) -> 9.6 | J56: =SUM(J51:J55) -> 11
A57: Total
A58: Total QA sprint | C58: =C11+C18+C22+C27+C32+C38+C49+C56 -> 75.15 | D58: =D11+D18+D22+D27+D32+D38+D49+D56 -> 100 | F58: =F11+F18+F22+F27+F32+F38+F49+F56 -> 73.05 | G58: =G11+G18+G22+G27+G32+G38+G49+G56 -> 100 | I58: =I11+I18+I22+I27+I32+I38+I49+I56 -> 65 | J58: =J11+J18+J22+J27+J32+J38+J49+J56 -> 100
A59: Note QA sprint | C59: =C58/D58 -> 0.7515 | F59: =F58/G58 -> 0.7305 | I59: =I58/J58 -> 0.65

Sheet Fonctionnalités
A2: Grille de correction LOG2995 - Hiver 2026
A4: Fonctionnalités
A6: Sprint 1
A7: Fonctionnalité | B7: Note | C7: Poids | D7: Note finale | E7: Correcteur | F7: Commentaires | H7: LOG2995-301 — Enregistrement et gestion des jeux (Sprint 1)
A8: Vue initiale | B8: 1 | C8: 5 | D8: =B8*C8 -> 5 | E8: Beaurel
A9: Vue d'administration | B9: 1 | C9: 15 | D9: =B9*C9 -> 15 | E9: Beaurel | H9: Critère | I9: Poids | J9: Note finale | K9: Points | L9: Commentaires
A10: Enregistrement et gestion des jeux (validation logicielle) | B10: 0.95 | C10: 20 | D10: =B10*C10 -> 19 | E10: Beaurel | F10: la visibilité est pas reset sur modif | H10: Stratégie de test | I10: 0.7 | J10: 10 | K10: 7 | L10: -0.3 - Le fichier edition.service.spec.ts est complètement vide, ce qui démontre une lacune dans la planification des tests. Le fichier dans edition-form/ est nommé 'edition-cell.component.spec.ts' au lieu de 'edition-form.component.spec.ts', créant de la confusion. Côté serveur, game.service.spec.ts (650+ lignes, 20+ tests) est excellent avec une validation exhaustive.
A11: Vue d'édition | B11: 0.95 | C11: 20 | D11: =B11*C11 -> 19 | E11: Beaurel | F11: on voit les noms mais pas de description | H11: Explication des cas limites | I11: 0.6 | J11: 10 | K11: 6 | L11: -0.4 - Côté serveur, les cas limites sont bien documentés (chaînes vides, espaces seuls, longueurs limites, titres dupliqués). Côté client, les noms de tests sont moins explicites — game.service.spec.ts ne décrit pas clairement les cas limites testés. Les commentaires informels ('// good', '// ooof') dans game-table et admin-socket suggèrent un manque de rigueur.
A12: Création ou édition d'un jeu | B12: 1 | C12: 20 | D12: =B12*C12 -> 20 | E12: Beaurel | H12: Cas limites | I12: 0.7 | J12: 20 | K12: 14 | L12: -0.3 - Bonne couverture serveur (game.service teste titre vide/espaces/trop long, description manquante, mode invalide, board manquant, titre dupliqué, visibilité invalide, jeu inexistant). Côté client, game-table couvre toggleVisibility erreur avec revert et deleteGame erreurs. Cependant, game.service client ne teste pas les IDs invalides/vides et administration.service n'a que 2 tests.
A13: Vue de création d'une partie | B13: 0.9 | C13: 20 | D13: =B13*C13 -> 18 | E13: Beaurel | F13: le personnage aléatoire n'attribue pas de bonus 1/3 | H13: Qualité des tests | I13: 0.7 | J13: 60 | K13: 42 | L13: -0.3 - Le serveur est de bonne qualité : game.controller.spec.ts (18+ tests supertest, tous codes HTTP) et game.service.spec.ts sont excellents. Board.service teste 14 cas de validation de grille. Cependant, edition.service.spec.ts est VIDE, certains tests dans game-edit-form combinent succès et erreur dans un seul 'it', et administration.service est minimal (2 tests seulement).
A14: Note finale pour le sprint | C14: =SUM(C8:C13) -> 100 | D14: =(SUM(D8:D13)+D16+D17)/C14 -> 0.96 | J14: Total | K14: 69
A15: Pénalités | B15: Note | C15: Poids | D15: Note finale | F15: Commentaires
A16: Crash | C16: -10 | D16: =B16*C16 -> 0
A17: Erreur de build ou de tests | C17: -15 | D17: =B17*C17 -> 0
A18: Validation Logicielle | B18: 0.69 | C18: 10 | D18: =C18*B18/10 -> 0.69
A20: Sprint 2 | H20: LOG2995-301 — Joindre une partie
A21: Fonctionnalité | B21: Note | C21: Poids | D21: Note finale | E21: Correcteur | F21: Commentaires
A22: Vue d'attente | B22: 1 | C22: 15 | D22: =B22*C22 -> 15 | E22: Alice | H22: Critère | I22: Poids | J22: Note finale | K22: Points | L22: Commentaires
A23: Joindre une partie (validation logicielle) | B23: 1 | C23: 15 | D23: =B23*C23 -> 15 | E23: Alice | H23: Stratégie de test | I23: 0.9 | J23: 10 | K23: 9 | L23: -0.1 - Excellente documentation de stratégie dans join-page et join-form-page (commentaires en en-tête expliquant l'approche d'isolation avec spies et RxJS Subject). Aucun fichier de test serveur pour la fonctionnalité Joindre une partie.
A24: Vue de jeu | B24: 1 | C24: 20 | D24: =B24*C24 -> 20 | E24: Alice | H24: Explication des cas limites | I24: 0.8 | J24: 10 | K24: 8 | L24: -0.2 - Bonne explication des cas limites côté client (stale data, socket update, cleanup onDestroy, missing activeGameId, abandoned players). Pas de documentation serveur.
A25: Partie classique - déplacement et tours | B25: 0.9 | C25: 30 | D25: =B25*C25 -> 27 | E25: Alice | F25: Le point de départ d'un joueur qui abandonne ne disparait pas. Tuiles accessibles affiche les tuiles du dernier tour au début. | H25: Cas limites | I25: 0.6 | J25: 20 | K25: 12 | L25: -0.4 - Seulement 17 tests au total, entièrement côté client (join-page 3 tests, join-form-page 14 tests). Aucun test serveur pour game-sockets.service.ts (JoinGame, LeaveWaitingRoom). Les cas limites client sont bons mais l'absence totale de tests serveur est pénalisante.
A26: Mode de débogage | B26: 1 | C26: 10 | D26: =B26*C26 -> 10 | E26: Alice | H26: Qualité des tests | I26: 0.7 | J26: 60 | K26: 42 | L26: -0.3 - Les tests client sont de très haute qualité : mocks isolés (6 services mockés dans join-form-page), noms descriptifs, assertions précises sur les appels de service et les changements d'état. Cependant, aucun test serveur pour la logique de jonction (game-sockets.service) réduit la note.
A27: Clavardage | B27: 0.95 | C27: 10 | D27: =B27*C27 -> 9.5 | E27: Alice | F27: On ne voit pas son nom dans l'entête de a zone de message | J27: Total | K27: 71
A28: Note finale pour le sprint | C28: =SUM(C22:C27) -> 100 | D28: =(SUM(D22:D27) + D30+D31+D32)/C28 -> 0.945 | J28: Note /100 | K28: 71
A29: Pénalités | B29: Note | C29: Poids | D29: Note finale | F29: Commentaires
A30: Crash | B30: 0.2 | C30: -10 | D30: =B30*C30 -> -2 | F30: Si on commence une partie pendant qu'un joueur est en "chargement de vue d'attente" le jeu est brisé
A31: Erreur de build ou de tests / déploiement erroné | B31: 0 | C31: -15 | D31: =B31*C31 -> 0
A32: Anciennes fonctionnalités brisées | B32: 0 | C32: -5 | D32: =B32*C32 -> 0
A33: Validation Logicielle | B33: 0.71 | C33: 10 | D33: =C33*B33/10 -> 0.71 | E33: Beaurel
A35: Sprint 3 | H35: LOG2995-301 — Combats et actions
A36: Fonctionnalité | B36: Note | C36: Poids | D36: Note finale | E36: Correcteur | F36: Commentaires
A37: Partie classique - combat et actions (validation logicielle) | B37: 0.9 | C37: 20 | D37: =B37*C37 -> 18 | E37: Zachary | F37: On peut se déplacer pendant un combat et on peut aussi terminer le tour de cette façon (condition mouvement et action à 0). Faire cela amene dans un état ou on ne peut plus faire d'action | H37: Critère | I37: Poids | J37: Note finale | K37: Points | L37: Commentaires
A38: Éditeur avancé | B38: 1 | C38: 20 | D38: =B38*C38 -> 20 | E38: Zachary | H38: Stratégie de test | I38: 1 | J38: 10 | K38: =I38*J38 -> 10
A39: Joueurs virtuels | B39: 1 | C39: 20 | D39: =B39*C39 -> 20 | E39: Zachary | H39: Explication des cas limites | I39: 1 | J39: 10 | K39: =I39*J39 -> 10
A40: Partie en mode CTF | B40: 1 | C40: 15 | D40: =B40*C40 -> 15 | E40: Zachary | H40: Cas limites | I40: 0.9 | J40: 20 | K40: =I40*J40 -> 18 | L40: le comportement des dés en mode debug n'est pas testé de façon isolée et vérifiable (on test le résultat du combat et non les dés)
A41: Journal de jeu | B41: 1 | C41: 10 | D41: =B41*C41 -> 10 | E41: Zachary | H41: Qualité des tests | I41: 0.9 | J41: 60 | K41: =I41*J41 -> 54 | L41: Vous avez plusieurs fixture dans le même cas de test, cela n'est pas vraiment dans la mentalité de tests unitaires (game-combat-outcome.component.spec.ts) Attention, certains de vos tests roulent lentement mais ce ne sont pas ceux évalués pour ce sprint
A42: Statistiques de fin de partie | B42: 0.9 | C42: 15 | D42: =B42*C42 -> 13.5 | E42: Zachary | F42: On ne peut pas correctement trier par victoire ou défaite | J42: Total | K42: =SUM(K38:K41) -> 92
A43: Note finale pour le sprint | C43: =SUM(C37:C42) -> 100 | D43: =(SUM(D37:D42) +D45+D46+D47)/C43 -> 0.965 | J43: Note /1 | K43: =K42/SUM(J38:J41) -> 0.92
A44: Pénalités | B44: Note | C44: Poids | D44: Note finale | F44: Commentaires
A45: Crash | B45: 0 | C45: -10 | D45: =B45*C45 -> 0
A46: Erreur de build ou de tests / déploiement erroné | B46: 0 | C46: -15 | D46: =B46*C46 -> 0
A47: Anciennes fonctionnalités brisées | B47: 0 | C47: -5 | D47: =B47*C47 -> 0
A48: Validation Logicielle | B48: =K43 -> 0.92 | C48: 10 | D48: =C48*B48/10 -> 0.92 | E48: Zachary
